artinator/__init__.py
artinator/cli.py
artinator/context.py
artinator/model.py
artinator/settings.py
artinator/tool.py
artinator/project/__init__.py
artinator/project/db.py
artinator/project/repo_map.py
artinator/project/scan_dir.py
artinator/project/scan_files.py
artinator-1.1.5.dist-info/METADATA
artinator-1.1.5.dist-info/WHEEL
artinator-1.1.5.dist-info/entry_points.txt
artinator-1.1.5.dist-info/top_level.txt
artinator-1.1.5.dist-info/RECORD
