Metadata-Version: 2.4
Name: artinator
Version: 1.1.5
Summary: CLI tool
Author-email: James Pic <jamespic@gmail.com>
License: MIT
Project-URL: Homepage, https://github.com/yourlabs/artinator
Keywords: cli
Requires-Python: >=3.6
Requires-Dist: cli2>=v6.0.0-rc13
Requires-Dist: litellm
